examples/advanced_logging.py
examples/conda_env.py
examples/custom_logviewer_with_docs.py
examples/daemon.py
examples/remote_logging.py
examples/shared_memory.py
teleprox/__init__.py
teleprox/bootstrap.py
teleprox/client.py
teleprox/process.py
teleprox/processspawner.py
teleprox/proxy.py
teleprox/qt.py
teleprox/qt_poll_thread.py
teleprox/qt_server.py
teleprox/qt_util.py
teleprox/serializer.py
teleprox/server.py
teleprox/shmem.py
teleprox/timer.py
teleprox/util.py
teleprox/log/__init__.py
teleprox/log/handler.py
teleprox/log/remote.py
teleprox/log/stdio.py
teleprox/log/logviewer/__init__.py
teleprox/log/logviewer/constants.py
teleprox/log/logviewer/export.py
teleprox/log/logviewer/filtering.py
teleprox/log/logviewer/log_model.py
teleprox/log/logviewer/proxies.py
teleprox/log/logviewer/utils.py
teleprox/log/logviewer/viewer.py
teleprox/log/logviewer/widgets.py
teleprox/log/logviewer/tests/test_child_filtering.py
teleprox/log/logviewer/tests/test_child_inheritance.py
teleprox/log/logviewer/tests/test_child_ui_behavior.py
teleprox/log/logviewer/tests/test_code_line_clicking.py
teleprox/log/logviewer/tests/test_column_data_mapping.py
teleprox/log/logviewer/tests/test_column_filtering.py
teleprox/log/logviewer/tests/test_column_filtering_integration.py
teleprox/log/logviewer/tests/test_context_menu_copy.py
teleprox/log/logviewer/tests/test_export.py
teleprox/log/logviewer/tests/test_filter_data_roles.py
teleprox/log/logviewer/tests/test_filter_proxies.py
teleprox/log/logviewer/tests/test_filter_utilities.py
teleprox/log/logviewer/tests/test_filtering_integration.py
teleprox/log/logviewer/tests/test_lazy_loading.py
teleprox/log/logviewer/tests/test_level_filtering.py
teleprox/log/logviewer/tests/test_search.py
teleprox/log/logviewer/tests/test_set_records.py
teleprox/log/logviewer/tests/test_sorting.py
teleprox/log/logviewer/tests/test_thread_safety.py
teleprox-2.1.2.dist-info/licenses/LICENSE
teleprox-2.1.2.dist-info/METADATA
teleprox-2.1.2.dist-info/WHEEL
teleprox-2.1.2.dist-info/top_level.txt
teleprox-2.1.2.dist-info/RECORD
