Metadata-Version: 2.4
Name: teleprox
Version: 2.1.2
Summary: Object proxies over TCP
Author: Luke Campagnola, Samuel Garcia, Martin Chase
License: Copyright (c) 2016, French National Center for Scientific Research (CNRS)
Project-URL: Homepage, http://github.com/campagnola/teleprox
Project-URL: Repository, http://github.com/campagnola/teleprox
Requires-Python: >=3.6
License-File: LICENSE
Requires-Dist: pyzmq
Requires-Dist: msgpack
Dynamic: license-file
